[
  {
    "time": "09:03",
    "user": "系统消息",
    "content": "[系统] \"sanyuan\"邀请\"知吾猪²⁰²⁶\"加入了群聊"
  },
  {
    "time": "09:03",
    "user": "系统消息",
    "content": "[系统] \"知吾猪²⁰²⁶\"与群里其他人都不是朋友关系，请注意隐私安全"
  },
  {
    "time": "10:58",
    "user": "zls",
    "content": "[捂脸]， sitor很急吗"
  },
  {
    "time": "10:58",
    "user": "zls",
    "content": "[图片]"
  },
  {
    "time": "11:00",
    "user": "稚",
    "content": "注入提示词，别着急收尾[旺柴]"
  },
  {
    "time": "11:01",
    "user": "CJ",
    "content": "[图片]"
  },
  {
    "time": "11:01",
    "user": "CJ",
    "content": "这对吗？Context Engineering在课程里面写着大脑供血"
  },
  {
    "time": "11:02",
    "user": "他",
    "content": "Sitor：俺寻思"
  },
  {
    "time": "11:03",
    "user": "L",
    "content": "我理解 sitor 里说的这个眼睛和就是字面意思， 课程里那个大脑供血是更深一层的"
  },
  {
    "time": "11:04",
    "user": "黄璇旋",
    "content": "感觉意会起来这两个都可以比喻"
  },
  {
    "time": "11:04",
    "user": "CJ",
    "content": "[图片]"
  },
  {
    "time": "11:05",
    "user": "黄璇旋",
    "content": "[动画表情]"
  },
  {
    "time": "11:05",
    "user": "黄璇旋",
    "content": "你骂它  它在讨好你"
  },
  {
    "time": "11:05",
    "user": "CJ",
    "content": "讨好型人格"
  },
  {
    "time": "11:05",
    "user": "黄璇旋",
    "content": "AI都是讨好型人格"
  },
  {
    "time": "11:05",
    "user": "CJ",
    "content": "[动画表情]"
  },
  {
    "time": "11:05",
    "user": "福合埕在逃牛肉丸",
    "content": "[图片]"
  },
  {
    "time": "11:05",
    "user": "福合埕在逃牛肉丸",
    "content": "你改一改看看呢"
  },
  {
    "time": "11:05",
    "user": "黄璇旋",
    "content": "6"
  },
  {
    "time": "11:06",
    "user": "CJ",
    "content": "哈哈哈哈笑死，挺温暖的"
  },
  {
    "time": "11:06",
    "user": "黄璇旋",
    "content": "你用严厉啊"
  },
  {
    "time": "11:06",
    "user": "福合埕在逃牛肉丸",
    "content": "面试官模式绝对没有给你脸的意思的"
  },
  {
    "time": "11:06",
    "user": "黄璇旋",
    "content": "我都不敢用面试官模式  第一遍看还是用严厉"
  },
  {
    "time": "11:06",
    "user": "黄璇旋",
    "content": "严厉也还好  没骂我"
  },
  {
    "time": "11:06",
    "user": "福合埕在逃牛肉丸",
    "content": "面试官模式压迫感一下子就上来了"
  },
  {
    "time": "11:06",
    "user": "福合埕在逃牛肉丸",
    "content": "不给你浑水摸鱼回答的余地"
  },
  {
    "time": "11:07",
    "user": "黄璇旋",
    "content": "严厉也还好  会指出错误然后解释正确的给你"
  },
  {
    "time": "11:57",
    "user": "系统消息",
    "content": "[系统] \"sanyuan\"邀请\"保护前额叶\"加入了群聊"
  },
  {
    "time": "11:57",
    "user": "系统消息",
    "content": "[系统] \"保护前额叶\"与群里其他人都不是朋友关系，请注意隐私安全"
  },
  {
    "time": "11:58",
    "user": "sanyuan",
    "content": "大家觉得在sitor 里面生成代码预览 是个刚需吗"
  },
  {
    "time": "11:58",
    "user": "sanyuan",
    "content": "现在还没有  coding 模式"
  },
  {
    "time": "11:59",
    "user": "sanyuan",
    "content": "后面整个沙箱 编程学习也可以搞起来了"
  },
  {
    "time": "12:00",
    "user": "小心甘",
    "content": "英文视频也能翻译成中文知识点吗，或者丢个项目地址，生成学习计划[旺柴]"
  },
  {
    "time": "12:01",
    "user": "小花花",
    "content": "你这样我真的抄不会了"
  },
  {
    "time": "12:02",
    "user": "回忆的。。。",
    "content": "@sanyuan 这里能不能支持基于历史提问记录，继续提问的？"
  },
  {
    "time": "12:02",
    "user": "回忆的。。。",
    "content": "[图片]"
  },
  {
    "time": "12:03",
    "user": "sanyuan",
    "content": "英文视频完全可以 没有问题 丢项目地址还不行，需要我做个 coding agent 来理解仓库 敬请期待哦"
  },
  {
    "time": "12:03",
    "user": "sanyuan",
    "content": "你是说追问吧"
  },
  {
    "time": "12:04",
    "user": "sanyuan",
    "content": "现在追问还在计划中"
  },
  {
    "time": "12:04",
    "user": "sanyuan",
    "content": "我目前是打算设计成追问最多三次"
  },
  {
    "time": "12:04",
    "user": "yinp",
    "content": "还有ppt的，现在不是准备html 范式嘛，生成没有字的ppt背景图然后文本贴入到对应的框中，可以直接分享网页，一个新的ppt 制作范式"
  },
  {
    "time": "12:04",
    "user": "yinp",
    "content": "[动画表情]"
  },
  {
    "time": "12:05",
    "user": "sanyuan",
    "content": "我现在不是有生成图解手记了吗？"
  },
  {
    "time": "12:05",
    "user": "yinp",
    "content": "不能修改文字"
  },
  {
    "time": "12:05",
    "user": "sanyuan",
    "content": "[图片]"
  },
  {
    "time": "12:05",
    "user": "yinp",
    "content": "[动画表情]"
  },
  {
    "time": "12:05",
    "user": "回忆的。。。",
    "content": "OK"
  },
  {
    "time": "12:05",
    "user": "yinp",
    "content": "现在才看到"
  },
  {
    "time": "12:06",
    "user": "sanyuan",
    "content": "[图片]"
  },
  {
    "time": "12:06",
    "user": "sanyuan",
    "content": "可以框选区域改图"
  },
  {
    "time": "12:06",
    "user": "sanyuan",
    "content": "@yinp"
  },
  {
    "time": "12:06",
    "user": "sanyuan",
    "content": "https://sitor.ai/slide-preview/c57023dc-7f9a-4f03-aa73-277fea5d2d61"
  },
  {
    "time": "12:08",
    "user": "yinp",
    "content": "改图贵跟直接html改字方便[憨笑]"
  },
  {
    "time": "12:09",
    "user": "sanyuan",
    "content": "[机智]"
  },
  {
    "time": "12:28",
    "user": "aTang",
    "content": "牛逼 这种图怎么做的啊"
  },
  {
    "time": "12:29",
    "user": "sanyuan",
    "content": "sitor 来做哈"
  },
  {
    "time": "12:29",
    "user": "sanyuan",
    "content": "用香蕉"
  },
  {
    "time": "14:20",
    "user": "sanyuan",
    "content": "[图片]"
  },
  {
    "time": "14:20",
    "user": "sanyuan",
    "content": "正在学习中"
  },
  {
    "time": "14:21",
    "user": "Lx",
    "content": "我也在看这个 哈哈"
  },
  {
    "time": "14:21",
    "user": "Lx",
    "content": "但是我是直接看"
  },
  {
    "time": "14:23",
    "user": "Rudy",
    "content": "这个视频封面怎么把郭宇拍这么难看"
  },
  {
    "time": "14:24",
    "user": "Lx",
    "content": "哈哈哈"
  },
  {
    "time": "14:26",
    "user": "财",
    "content": "我也去学习去"
  },
  {
    "time": "14:27",
    "user": "sanyuan",
    "content": "[图片]"
  },
  {
    "time": "14:27",
    "user": "sanyuan",
    "content": "太屌了我去"
  },
  {
    "time": "14:28",
    "user": "sanyuan",
    "content": "私教这个认知实在是让人叹为观止"
  },
  {
    "time": "14:28",
    "user": "sanyuan",
    "content": "我现在把教学节奏调整了 一开始会跟你敞开聊"
  },
  {
    "time": "14:28",
    "user": "L",
    "content": "你是最不应该害怕的[阴险]"
  },
  {
    "time": "14:28",
    "user": "L",
    "content": "群友害怕 你都不该害怕"
  },
  {
    "time": "14:40",
    "user": "光影",
    "content": "这个私教解读功能上线啦？"
  },
  {
    "time": "14:42",
    "user": "sanyuan",
    "content": "@光影 上线了"
  },
  {
    "time": "14:43",
    "user": "财",
    "content": "哎呦我没看到"
  },
  {
    "time": "14:43",
    "user": "sanyuan",
    "content": "首页哈 @光影  @财"
  },
  {
    "time": "14:43",
    "user": "sanyuan",
    "content": "可以上传文件和视频链接"
  },
  {
    "time": "14:44",
    "user": "Rudy",
    "content": "说到首页 突然想到昨天发现个bug  这个图预览的时候 有层级问题  @sanyuan"
  },
  {
    "time": "14:44",
    "user": "Rudy",
    "content": "[图片]"
  },
  {
    "time": "14:44",
    "user": "光影",
    "content": "哦哦，看到了，难怪我说我直接开对话没有看到，我也试试"
  },
  {
    "time": "14:44",
    "user": "光影",
    "content": "[图片]"
  },
  {
    "time": "14:44",
    "user": "sanyuan",
    "content": "ok"
  },
  {
    "time": "14:45",
    "user": "财",
    "content": "看到了"
  },
  {
    "time": "14:53",
    "user": "光影",
    "content": "为啥我的这样 @sanyuan"
  },
  {
    "time": "14:53",
    "user": "光影",
    "content": "[图片]"
  },
  {
    "time": "14:56",
    "user": "sanyuan",
    "content": "稍等下 @光影"
  },
  {
    "time": "15:15",
    "user": "系统消息",
    "content": "[系统] \"sanyuan\"邀请\"- chen。\"加入了群聊"
  },
  {
    "time": "15:15",
    "user": "系统消息",
    "content": "[系统] \"- chen。\"与群里其他人都不是朋友关系，请注意隐私安全"
  },
  {
    "time": "15:46",
    "user": "sanyuan",
    "content": "@光影 现在好了"
  },
  {
    "time": "15:46",
    "user": "sanyuan",
    "content": "YouTube接口出了点问题刚刚"
  },
  {
    "time": "15:48",
    "user": "光影",
    "content": "可以了，可以了"
  },
  {
    "time": "17:48",
    "user": "稚",
    "content": "@sanyuan"
  },
  {
    "time": "17:48",
    "user": "系统消息",
    "content": "[系统] \"稚\" 撤回了一条消息"
  },
  {
    "time": "17:49",
    "user": "稚",
    "content": "也没留地方给我说啊"
  },
  {
    "time": "17:49",
    "user": "稚",
    "content": "[捂脸]"
  },
  {
    "time": "17:49",
    "user": "稚",
    "content": "[图片]"
  },
  {
    "time": "18:17",
    "user": "sanyuan",
    "content": "正在修复这个问题 搞完了@你"
  }
]